fidding_hive_executor_py-1.1.9.dev1.dist-info/METADATA
fidding_hive_executor_py-1.1.9.dev1.dist-info/RECORD
fidding_hive_executor_py-1.1.9.dev1.dist-info/WHEEL
fidding_hive_executor_py-1.1.9.dev1.dist-info/top_level.txt
hive/__init__.py
hive/exceptions.py
hive/executor.py
