Metadata-Version: 2.1
Name: fidding-hive-executor-py
Version: 1.1.9.dev1
Summary: A hive client python project
Home-page: https://github.com/fidding/hive-executor-py
Author: fidding
Author-email: 395455856@qq.com
License: MIT
Keywords: hive client python
Platform: UNKNOWN
Classifier: Development Status :: 4 - Beta
Classifier: Intended Audience :: Developers
Classifier: Topic :: Software Development :: Build Tools
Classifier: License :: OSI Approved :: MIT License
Classifier: Programming Language :: Python :: 2.6
Classifier: Programming Language :: Python :: 2.7
Classifier: Programming Language :: Python :: 3
Classifier: Programming Language :: Python :: 3.3
Classifier: Programming Language :: Python :: 3.4
Classifier: Programming Language :: Python :: 3.5
Requires-Dist: common-utils
